jphelper/__init__.py
jphelper/constant.py
jphelper/jphelper.py
jphelper/number.py
jphelper-0.9.1.dist-info/DESCRIPTION.rst
jphelper-0.9.1.dist-info/METADATA
jphelper-0.9.1.dist-info/RECORD
jphelper-0.9.1.dist-info/WHEEL
jphelper-0.9.1.dist-info/metadata.json
jphelper-0.9.1.dist-info/top_level.txt
