Metadata-Version: 2.0
Name: jphelper
Version: 0.9.1
Summary: A collection of japanese text and number manipulation tools.
Home-page: https://github.com/michaeldvr/jphelper
Author: Michael Devara
Author-email: michael.devara@gmail.com
License: MIT
Keywords: japanese,utility,utils,tools
Platform: any
Classifier: Programming Language :: Python
Classifier: Programming Language :: Python :: 3
Classifier: License :: OSI Approved :: MIT License
Classifier: Environment :: Other Environment
Classifier: Natural Language :: Japanese
Classifier: Operating System :: OS Independent
Classifier: Topic :: Utilities
Requires-Python: >=3
